{"boolStats":[{"key":22,"value":1},{"key":99,"value":0},{"key":85,"value":1},{"key":91,"value":1}],"didStats":[{"key":6,"value":67111919},{"key":3,"value":536870932},{"key":22,"value":872415275},{"key":1,"value":33560652},{"key":8,"value":100690007},{"key":28,"value":4447},{"key":52,"value":100676436}],"floatStats":[{"key":39,"value":0.600000023841858},{"key":152,"value":1.39999993145466},{"key":144,"value":0.125999997198582},{"key":29,"value":1.17999994754791},{"key":5,"value":-0.0666666701436043},{"key":150,"value":1.015},{"key":149,"value":1.005}],"int64Stats":[{"key":4,"value":100000000000},{"key":5,"value":2000000000}],"intStats":[{"key":93,"value":1044},{"key":1,"value":32768},{"key":19,"value":19428},{"key":319,"value":50},{"key":383,"value":1},{"key":16,"value":6291461},{"key":158,"value":2},{"key":94,"value":16},{"key":18,"value":65},{"key":9,"value":16777216},{"key":105,"value":6},{"key":5,"value":50},{"key":151,"value":2},{"key":131,"value":41},{"key":160,"value":385},{"key":177,"value":3},{"key":106,"value":370},{"key":114,"value":0},{"key":178,"value":41},{"key":179,"value":1},{"key":115,"value":0},{"key":171,"value":10},{"key":107,"value":1109},{"key":108,"value":1634},{"key":172,"value":5},{"key":109,"value":399},{"key":45,"value":64},{"key":110,"value":0},{"key":159,"value":34},{"key":384,"value":1},{"key":320,"value":1},{"key":166,"value":101},{"key":265,"value":139}],"spellbook":[{"key":5427,"value":{"casting_likelihood":2.0}},{"key":4455,"value":{"casting_likelihood":2.0}},{"key":2267,"value":{"casting_likelihood":2.0}},{"key":1480,"value":{"casting_likelihood":2.0}},{"key":2520,"value":{"casting_likelihood":2.0}},{"key":4689,"value":{"casting_likelihood":2.0}},{"key":2516,"value":{"casting_likelihood":2.0}},{"key":4510,"value":{"casting_likelihood":2.0}},{"key":2287,"value":{"casting_likelihood":2.0}},{"key":3259,"value":{"casting_likelihood":2.0}},{"key":69,"value":{"casting_likelihood":2.0}},{"key":4447,"value":{"casting_likelihood":2.0}},{"key":2578,"value":{"casting_likelihood":2.0}},{"key":6102,"value":{"casting_likelihood":2.0}},{"key":4400,"value":{"casting_likelihood":2.0}},{"key":4705,"value":{"casting_likelihood":2.0}},{"key":634,"value":{"casting_likelihood":2.0}},{"key":4451,"value":{"casting_likelihood":2.0}},{"key":2507,"value":{"casting_likelihood":2.0}},{"key":6098,"value":{"casting_likelihood":2.0}},{"key":5881,"value":{"casting_likelihood":2.0}},{"key":2091,"value":{"casting_likelihood":2.0}},{"key":2559,"value":{"casting_likelihood":2.0}},{"key":2128,"value":{"casting_likelihood":2.0}},{"key":4439,"value":{"casting_likelihood":2.0}},{"key":4329,"value":{"casting_likelihood":2.0}},{"key":4418,"value":{"casting_likelihood":2.0}},{"key":4684,"value":{"casting_likelihood":2.0}},{"key":610,"value":{"casting_likelihood":2.0}},{"key":2527,"value":{"casting_likelihood":2.0}},{"key":3965,"value":{"casting_likelihood":2.0}},{"key":63,"value":{"casting_likelihood":2.0}},{"key":3251,"value":{"casting_likelihood":2.0}},{"key":2526,"value":{"casting_likelihood":2.0}},{"key":4582,"value":{"casting_likelihood":2.0}},{"key":2117,"value":{"casting_likelihood":2.0}},{"key":5429,"value":{"casting_likelihood":2.0}},{"key":2576,"value":{"casting_likelihood":2.0}},{"key":2146,"value":{"casting_likelihood":2.0}},{"key":4433,"value":{"casting_likelihood":2.0}},{"key":2574,"value":{"casting_likelihood":2.0}},{"key":2524,"value":{"casting_likelihood":2.0}},{"key":2573,"value":{"casting_likelihood":2.0}},{"key":4564,"value":{"casting_likelihood":2.0}},{"key":2101,"value":{"casting_likelihood":2.0}},{"key":2144,"value":{"casting_likelihood":2.0}},{"key":2511,"value":{"casting_likelihood":2.0}},{"key":4403,"value":{"casting_likelihood":2.0}},{"key":3200,"value":{"casting_likelihood":2.0}},{"key":2140,"value":{"casting_likelihood":2.0}},{"key":4638,"value":{"casting_likelihood":2.0}},{"key":2615,"value":{"casting_likelihood":2.0}},{"key":2529,"value":{"casting_likelihood":2.0}},{"key":4409,"value":{"casting_likelihood":2.0}},{"key":2525,"value":{"casting_likelihood":2.0}},{"key":4700,"value":{"casting_likelihood":2.0}},{"key":91,"value":{"casting_likelihood":2.0}},{"key":97,"value":{"casting_likelihood":2.0}},{"key":4911,"value":{"casting_likelihood":2.0}},{"key":1605,"value":{"casting_likelihood":2.0}},{"key":2323,"value":{"casting_likelihood":2.0}},{"key":4696,"value":{"casting_likelihood":2.0}},{"key":5428,"value":{"casting_likelihood":2.0}},{"key":2132,"value":{"casting_likelihood":2.0}},{"key":1450,"value":{"casting_likelihood":2.0}},{"key":2122,"value":{"casting_likelihood":2.0}},{"key":6104,"value":{"casting_likelihood":2.0}},{"key":2502,"value":{"casting_likelihood":2.0}},{"key":85,"value":{"casting_likelihood":2.0}},{"key":683,"value":{"casting_likelihood":2.0}},{"key":3250,"value":{"casting_likelihood":2.0}},{"key":2571,"value":{"casting_likelihood":2.0}},{"key":2215,"value":{"casting_likelihood":2.0}},{"key":3258,"value":{"casting_likelihood":2.0}},{"key":4673,"value":{"casting_likelihood":2.0}},{"key":2136,"value":{"casting_likelihood":2.0}},{"key":2249,"value":{"casting_likelihood":2.0}},{"key":4414,"value":{"casting_likelihood":2.0}},{"key":4443,"value":{"casting_likelihood":2.0}},{"key":2515,"value":{"casting_likelihood":2.0}},{"key":2555,"value":{"casting_likelihood":2.0}},{"key":4670,"value":{"casting_likelihood":2.0}},{"key":2067,"value":{"casting_likelihood":2.0}},{"key":2195,"value":{"casting_likelihood":2.0}},{"key":2588,"value":{"casting_likelihood":2.0}},{"key":4305,"value":{"casting_likelihood":2.0}},{"key":6042,"value":{"casting_likelihood":2.0}},{"key":4530,"value":{"casting_likelihood":2.0}},{"key":2506,"value":{"casting_likelihood":2.0}},{"key":80,"value":{"casting_likelihood":2.0}},{"key":4663,"value":{"casting_likelihood":2.0}},{"key":74,"value":{"casting_likelihood":2.0}},{"key":5880,"value":{"casting_likelihood":2.0}},{"key":4457,"value":{"casting_likelihood":2.0}},{"key":6074,"value":{"casting_likelihood":2.0}},{"key":1426,"value":{"casting_likelihood":2.0}},{"key":6125,"value":{"casting_likelihood":2.0}},{"key":2570,"value":{"casting_likelihood":2.0}},{"key":2610,"value":{"casting_likelihood":2.0}}],"stringStats":[{"key":1,"value":"Electric Staff"}],"wcid":37219,"weenieType":35}